Metadata-Version: 1.0
Name: dsnd-probability-distributions-shweta
Version: 1.0
Summary: Gaussian and Binomial distributions
Home-page: UNKNOWN
Author: Shweta
Author-email: shweta.universidad@gmail.com
License: UNKNOWN
Platform: UNKNOWN
